odoo/addons/web_advanced_search_wildcard/README.rst
odoo/addons/web_advanced_search_wildcard/__init__.py
odoo/addons/web_advanced_search_wildcard/__manifest__.py
odoo/addons/web_advanced_search_wildcard/i18n/ca.po
odoo/addons/web_advanced_search_wildcard/i18n/de.po
odoo/addons/web_advanced_search_wildcard/i18n/es.po
odoo/addons/web_advanced_search_wildcard/i18n/fi.po
odoo/addons/web_advanced_search_wildcard/i18n/fr.po
odoo/addons/web_advanced_search_wildcard/i18n/it.po
odoo/addons/web_advanced_search_wildcard/i18n/lt.po
odoo/addons/web_advanced_search_wildcard/i18n/pt.po
odoo/addons/web_advanced_search_wildcard/i18n/pt_BR.po
odoo/addons/web_advanced_search_wildcard/i18n/sl.po
odoo/addons/web_advanced_search_wildcard/i18n/tr.po
odoo/addons/web_advanced_search_wildcard/i18n/web_advanced_search_wildcard.pot
odoo/addons/web_advanced_search_wildcard/readme/CONTRIBUTORS.rst
odoo/addons/web_advanced_search_wildcard/readme/DESCRIPTION.rst
odoo/addons/web_advanced_search_wildcard/readme/USAGE.rst
odoo/addons/web_advanced_search_wildcard/static/description/icon.png
odoo/addons/web_advanced_search_wildcard/static/description/index.html
odoo/addons/web_advanced_search_wildcard/static/description/screenshot.png
odoo/addons/web_advanced_search_wildcard/static/src/js/search.js
odoo/addons/web_advanced_search_wildcard/views/template.xml
odoo12_addon_web_advanced_search_wildcard-12.0.1.0.0.99.dev18.dist-info/METADATA
odoo12_addon_web_advanced_search_wildcard-12.0.1.0.0.99.dev18.dist-info/WHEEL
odoo12_addon_web_advanced_search_wildcard-12.0.1.0.0.99.dev18.dist-info/top_level.txt
odoo12_addon_web_advanced_search_wildcard-12.0.1.0.0.99.dev18.dist-info/RECORD
